INSTALL
LICENSE
MANIFEST.in
README.markdown
setup.cfg
setup.py
fapws/__init__.py
fapws/_evwsgi.c
fapws/base.py
fapws/common.h
fapws/config.py
fapws/extra.c
fapws/extra.h
fapws/mainloop.c
fapws/mainloop.h
fapws/wsgi.c
fapws/wsgi.h
fapws/contrib/__init__.py
fapws/contrib/cgiapp.py
fapws/contrib/django_handler.py
fapws/contrib/headers.py
fapws/contrib/log.py
fapws/contrib/views.py
fapws/contrib/zip.py
fapws3.egg-info/PKG-INFO
fapws3.egg-info/SOURCES.txt
fapws3.egg-info/dependency_links.txt
fapws3.egg-info/entry_points.txt
fapws3.egg-info/not-zip-safe
fapws3.egg-info/top_level.txt