Metadata-Version: 1.0
Name: fapws3
Version: 0.8.1.dev
Summary: Fast Asynchronous Python Web Server
Home-page: http://www.fapws.org
Author: William
Author-email: william.os4y@gmail.com
License: GPL
Platform: UNKNOWN
Classifier: Development Status :: 4 - Beta
Classifier: Environment :: Web Environment
Classifier: License :: OSI Approved :: GNU General Public License (GPL)
Classifier: Programming Language :: C
Classifier: Programming Language :: Python
Classifier: Topic :: Internet :: WWW/HTTP :: HTTP Servers
Classifier: Topic :: Internet :: WWW/HTTP :: WSGI :: Server
